[
    {
        "title" : "Piano Roll",
        "image" : "https://imagizer.imageshack.com/img922/6885/5GlV21.png",
        "description" : "loream ipsum in dolor..."
    },
    {
        "title" : "Step Sequencer",
        "image" : "https://imagizer.imageshack.com/img924/3204/5bQT1k.png",
        "description" : "loream ipsum in dolor..."
    },
    {
        "title" : "Sampler",
        "image" : "https://imagizer.imageshack.com/img924/3134/Xxc1GN.png",
        "description" : "loream ipsum in dolor..."
    }
]